Workbook

Sheet Raw Data
A1: Transaction_ID | B1: Date | C1: Customer_ID | D1: Customer_Name | E1: Product_ID | F1: Product_Name | G1: Category | H1: Quantity | I1: Unit_Price | J1: Payment_Method | K1: Region | L1: Customer_Segment | M1: Customer_Since | N1: Total_Amount | O1: Month_Start | P1: Tenure_Years (DATEDIF) | Q1: Filter_Match_No
A2: TRX0155 | B2: 45393 | C2: CUST023 | D2: Paul Baker | E2: P009 | F2: Monitor | G2: Electronics | H2: 3 | I2: 249.99 | J2: Cash | K2: Central | L2: Basic | M2: 44425 | N2: 749.97 | O2: =DATE(YEAR(B2),MONTH(B2),1) -> 45383 | P2: =DATEDIF(M2,B2,"Y") -> 2 | Q2: =IF(AND(OR(Analysis!$C$5="All",K2=Analysis!$C$5),OR(Analysis!$C$6="All",G2=Analysis!$C$6)),MAX(Q$1:Q1)+1,"") -> 1
A3: TRX0023 | B3: 45396 | C3: CUST013 | D3: Joseph Jackson | E3: P009 | F3: Monitor | G3: Electronics | H3: 3 | I3: 249.99 | J3: Credit Card | K3: Central | L3: Premium | M3: 44575 | N3: 749.97 | O3: =DATE(YEAR(B3),MONTH(B3),1) -> 45383 | P3: =DATEDIF(M3,B3,"Y") -> 2 | Q3: =IF(AND(OR(Analysis!$C$5="All",K3=Analysis!$C$5),OR(Analysis!$C$6="All",G3=Analysis!$C$6)),MAX(Q$1:Q2)+1,"") -> 2
A4: TRX0139 | B4: 45399 | C4: CUST021 | D4: Kevin Scott | E4: P005 | F4: Blender | G4: Appliances | H4: 3 | I4: 59.99 | J4: PayPal | K4: South | L4: Standard | M4: 45262 | N4: 179.97 | O4: =DATE(YEAR(B4),MONTH(B4),1) -> 45383 | P4: =DATEDIF(M4,B4,"Y") -> 0 | Q4: =IF(AND(OR(Analysis!$C$5="All",K4=Analysis!$C$5),OR(Analysis!$C$6="All",G4=Analysis!$C$6)),MAX(Q$1:Q3)+1,"") -> 3
A5: TRX0043 | B5: 45400 | C5: CUST046 | D5: Kathleen Bennett | E5: P005 | F5: Blender | G5: Appliances | H5: 3 | I5: 59.99 | J5: Cash | K5: North | L5: Premium | M5: 45114 | N5: 179.97 | O5: =DATE(YEAR(B5),MONTH(B5),1) -> 45383 | P5: =DATEDIF(M5,B5,"Y") -> 0 | Q5: =IF(AND(OR(Analysis!$C$5="All",K5=Analysis!$C$5),OR(Analysis!$C$6="All",G5=Analysis!$C$6)),MAX(Q$1:Q4)+1,"") -> 4
A6: TRX0212 | B6: 45400 | C6: CUST003 | D6: Michael Brown | E6: P008 | F6: Bookshelf | G6: Furniture | H6: 5 | I6: 149.99 | J6: Credit Card | K6: North | L6: Premium | M6: 45295 | N6: 749.95 | O6: =DATE(YEAR(B6),MONTH(B6),1) -> 45383 | P6: =DATEDIF(M6,B6,"Y") -> 0 | Q6: =IF(AND(OR(Analysis!$C$5="All",K6=Analysis!$C$5),OR(Analysis!$C$6="All",G6=Analysis!$C$6)),MAX(Q$1:Q5)+1,"") -> 5
A7: TRX0092 | B7: 45403 | C7: CUST024 | D7: Dorothy Nelson | E7: P005 | F7: Blender | G7: Appliances | H7: 2 | I7: 59.99 | J7: Cash | K7: West | L7: Standard | M7: 44746 | N7: 119.98 | O7: =DATE(YEAR(B7),MONTH(B7),1) -> 45383 | P7: =DATEDIF(M7,B7,"Y") -> 1 | Q7: =IF(AND(OR(Analysis!$C$5="All",K7=Analysis!$C$5),OR(Analysis!$C$6="All",G7=Analysis!$C$6)),MAX(Q$1:Q6)+1,"") -> 6
A8: TRX0193 | B8: 45403 | C8: CUST024 | D8: Dorothy Nelson | E8: P003 | F8: Headphones | G8: Electronics | H8: 5 | I8: 149.99 | J8: Credit Card | K8: Central | L8: Standard | M8: 44418 | N8: 749.95 | O8: =DATE(YEAR(B8),MONTH(B8),1) -> 45383 | P8: =DATEDIF(M8,B8,"Y") -> 2 | Q8: =IF(AND(OR(Analysis!$C$5="All",K8=Analysis!$C$5),OR(Analysis!$C$6="All",G8=Analysis!$C$6)),MAX(Q$1:Q7)+1,"") -> 7
A9: TRX0240 | B9: 45403 | C9: CUST017 | D9: Charles Allen | E9: P005 | F9: Blender | G9: Appliances | H9: 3 | I9: 59.99 | J9: Debit Card | K9: South | L9: Basic | M9: 45007 | N9: 179.97 | O9: =DATE(YEAR(B9),MONTH(B9),1) -> 45383 | P9: =DATEDIF(M9,B9,"Y") -> 1 | Q9: =IF(AND(OR(Analysis!$C$5="All",K9=Analysis!$C$5),OR(Analysis!$C$6="All",G9=Analysis!$C$6)),MAX(Q$1:Q8)+1,"") -> 8
A10: TRX0135 | B10: 45405 | C10: CUST009 | D10: Robert Thomas | E10: P001 | F10: Laptop | G10: Electronics | H10: 3 | I10: 899.99 | J10: PayPal | K10: East | L10: Standard | M10: 45299 | N10: 2699.97 | O10: =DATE(YEAR(B10),MONTH(B10),1) -> 45383 | P10: =DATEDIF(M10,B10,"Y") -> 0 | Q10: =IF(AND(OR(Analysis!$C$5="All",K10=Analysis!$C$5),OR(Analysis!$C$6="All",G10=Analysis!$C$6)),MAX(Q$1:Q9)+1,"") -> 9
A11: TRX0185 | B11: 45408 | C11: CUST026 | D11: Karen Hill | E11: P005 | F11: Blender | G11: Appliances | H11: 3 | I11: 59.99 | J11: Cash | K11: West | L11: Premium | M11: 45207 | N11: 179.97 | O11: =DATE(YEAR(B11),MONTH(B11),1) -> 45383 | P11: =DATEDIF(M11,B11,"Y") -> 0 | Q11: =IF(AND(OR(Analysis!$C$5="All",K11=Analysis!$C$5),OR(Analysis!$C$6="All",G11=Analysis!$C$6)),MAX(Q$1:Q10)+1,"") -> 10
A12: TRX0138 | B12: 45408 | C12: CUST022 | D12: Susan Green | E12: P008 | F12: Bookshelf | G12: Furniture | H12: 1 | I12: 149.99 | J12: Credit Card | K12: West | L12: Standard | M12: 45103 | N12: 149.99 | O12: =DATE(YEAR(B12),MONTH(B12),1) -> 45383 | P12: =DATEDIF(M12,B12,"Y") -> 0 | Q12: =IF(AND(OR(Analysis!$C$5="All",K12=Analysis!$C$5),OR(Analysis!$C$6="All",G12=Analysis!$C$6)),MAX(Q$1:Q11)+1,"") -> 11
A13: TRX0209 | B13: 45408 | C13: CUST046 | D13: Kathleen Bennett | E13: P008 | F13: Bookshelf | G13: Furniture | H13: 5 | I13: 149.99 | J13: Debit Card | K13: North | L13: Basic | M13: 44830 | N13: 749.95 | O13: =DATE(YEAR(B13),MONTH(B13),1) -> 45383 | P13: =DATEDIF(M13,B13,"Y") -> 1 | Q13: =IF(AND(OR(Analysis!$C$5="All",K13=Analysis!$C$5),OR(Analysis!$C$6="All",G13=Analysis!$C$6)),MAX(Q$1:Q12)+1,"") -> 12
... A251: TRX0064 | B251: 45758 | C251: CUST031 | D251: Steven Turner | E251: P010 | F251: Keyboard | G251: Electronics | H251: 3 | I251: 89.99 | J251: Debit Card | K251: North | L251: Premium | M251: 44878 | N251: 269.97 | O251: =DATE(YEAR(B251),MONTH(B251),1) -> 45748 | P251: =DATEDIF(M251,B251,"Y") -> 2 | Q251: =IF(AND(OR(Analysis!$C$5="All",K251=Analysis!$C$5),OR(Analysis!$C$6="All",G251=Analysis!$C$6)),MAX(Q$1:Q250)+1,"") -> 250

Sheet Analysis
A1: Analysis - Formula Workings (Data Intelligence Dashboard)
A4: 1. Date & Time Functions, Timestamp and Filter Selectors
A5: Filter: Region | C5: All
A6: Filter: Category | C6: All
A7: Today (TODAY) | C7: =TODAY() -> 46310 | E7: Timestamp (NOW + iterative calc)
A8: Now (NOW) | C8: =NOW() -> 46310.46
A9: First transaction date | C9: =MIN('Raw Data'!$B$2:$B$251) -> 45393 | F9: Entry: | G9: Sample entry
A10: Last transaction date | C10: =MAX('Raw Data'!$B$2:$B$251) -> 45758 | F10: Timestamp: | G10: =IF(G9<>"",IF(N(G10)=0,NOW(),G10),"") -> 46310.186
A11: Data span (DATEDIF, months) | C11: =DATEDIF(C9,C10,"M") -> 12
A12: End of last month (EOMONTH) | C12: =EOMONTH(C10,0) -> 45777
A13: End of next month (EOMONTH +1) | C13: =EOMONTH(C10,1) -> 45808
A14: Days since last sale (DATEDIF) | C14: =DATEDIF(C10,C7,"D") -> 552
A16: 2. Summary KPIs
A17: Total Revenue | C17: =SUM('Raw Data'!$N$2:$N$251) -> 229192.47
A18: Total Transactions | C18: =COUNTA('Raw Data'!$A$2:$A$251) -> 250
A19: Average Order Value | C19: =C17/C18 -> 916.76988
A20: Units Sold | C20: =SUM('Raw Data'!$H$2:$H$251) -> 753
A21: Unique Customers | C21: =SUMPRODUCT(1/COUNTIF('Raw Data'!$C$2:$C$251,'Raw Data'!$C$2:$C$251)) -> 50
A22: Filtered Revenue (Region/Category selection) | C22: =SUMIFS('Raw Data'!$N$2:$N$251,'Raw Data'!$K$2:$K$251,IF($C$5="All","*",$C$5),'Raw Data'!$G$2:$G$251,IF($C$6="All","*",$C$6)) -> 229192.47
A23: Filtered Transactions | C23: =COUNTIFS('Raw Data'!$K$2:$K$251,IF($C$5="All","*",$C$5),'Raw Data'!$G$2:$G$251,IF($C$6="All","*",$C$6)) -> 250
A26: 3. Regional Sales (Pivot-style)
A27: Region | B27: Revenue | C27: Transactions | D27: Units | E27: Avg Order | F27: % of Revenue | G27: Rank
A28: Central | B28: =SUMIFS('Raw Data'!$N$2:$N$251,'Raw Data'!$K$2:$K$251,A28) -> 41288.34 | C28: =COUNTIFS('Raw Data'!$K$2:$K$251,A28) -> 54 | D28: =SUMIFS('Raw Data'!$H$2:$H$251,'Raw Data'!$K$2:$K$251,A28) -> 166 | E28: =IFERROR(B28/C28,0) -> 764.59889 | F28: =B28/$C$17 -> 0.18014702 | G28: =RANK(B28,$B$28:$B$32) -> 4
A29: East | B29: =SUMIFS('Raw Data'!$N$2:$N$251,'Raw Data'!$K$2:$K$251,A29) -> 59288.39 | C29: =COUNTIFS('Raw Data'!$K$2:$K$251,A29) -> 48 | D29: =SUMIFS('Raw Data'!$H$2:$H$251,'Raw Data'!$K$2:$K$251,A29) -> 161 | E29: =IFERROR(B29/C29,0) -> 1235.1748 | F29: =B29/$C$17 -> 0.25868385 | G29: =RANK(B29,$B$28:$B$32) -> 1
A30: North | B30: =SUMIFS('Raw Data'!$N$2:$N$251,'Raw Data'!$K$2:$K$251,A30) -> 50808.31 | C30: =COUNTIFS('Raw Data'!$K$2:$K$251,A30) -> 59 | D30: =SUMIFS('Raw Data'!$H$2:$H$251,'Raw Data'!$K$2:$K$251,A30) -> 169 | E30: =IFERROR(B30/C30,0) -> 861.1578 | F30: =B30/$C$17 -> 0.22168403 | G30: =RANK(B30,$B$28:$B$32) -> 2
A31: South | B31: =SUMIFS('Raw Data'!$N$2:$N$251,'Raw Data'!$K$2:$K$251,A31) -> 36398.75 | C31: =COUNTIFS('Raw Data'!$K$2:$K$251,A31) -> 42 | D31: =SUMIFS('Raw Data'!$H$2:$H$251,'Raw Data'!$K$2:$K$251,A31) -> 125 | E31: =IFERROR(B31/C31,0) -> 866.6369 | F31: =B31/$C$17 -> 0.15881303 | G31: =RANK(B31,$B$28:$B$32) -> 5
A32: West | B32: =SUMIFS('Raw Data'!$N$2:$N$251,'Raw Data'!$K$2:$K$251,A32) -> 41408.68 | C32: =COUNTIFS('Raw Data'!$K$2:$K$251,A32) -> 47 | D32: =SUMIFS('Raw Data'!$H$2:$H$251,'Raw Data'!$K$2:$K$251,A32) -> 132 | E32: =IFERROR(B32/C32,0) -> 881.03574 | F32: =B32/$C$17 -> 0.18067208 | G32: =RANK(B32,$B$28:$B$32) -> 3
A33: Total | B33: =SUM(B28:B32) -> 229192.47 | C33: =SUM(C28:C32) -> 250 | D33: =SUM(D28:D32) -> 753 | F33: =SUM(F28:F32) -> 1
A35: 4. Category Sales
A36: Category | B36: Revenue | C36: Transactions | D36: Units | E36: Avg Order | F36: % of Revenue | G36: Rank
A37: Appliances | B37: =SUMIFS('Raw Data'!$N$2:$N$251,'Raw Data'!$G$2:$G$251,A37) -> 8338.74 | C37: =COUNTIFS('Raw Data'!$G$2:$G$251,A37) -> 43 | D37: =SUMIFS('Raw Data'!$H$2:$H$251,'Raw Data'!$G$2:$G$251,A37) -> 126 | E37: =IFERROR(B37/C37,0) -> 193.92419 | F37: =B37/$C$17 -> 0.036383132 | G37: =RANK(B37,$B$37:$B$39) -> 3
A38: Electronics | B38: =SUMIFS('Raw Data'!$N$2:$N$251,'Raw Data'!$G$2:$G$251,A38) -> 171756.05 | C38: =COUNTIFS('Raw Data'!$G$2:$G$251,A38) -> 131 | D38: =SUMIFS('Raw Data'!$H$2:$H$251,'Raw Data'!$G$2:$G$251,A38) -> 395 | E38: =IFERROR(B38/C38,0) -> 1311.1149 | F38: =B38/$C$17 -> 0.74939657 | G38: =RANK(B38,$B$37:$B$39) -> 1
A39: Furniture | B39: =SUMIFS('Raw Data'!$N$2:$N$251,'Raw Data'!$G$2:$G$251,A39) -> 49097.68 | C39: =COUNTIFS('Raw Data'!$G$2:$G$251,A39) -> 76 | D39: =SUMIFS('Raw Data'!$H$2:$H$251,'Raw Data'!$G$2:$G$251,A39) -> 232 | E39: =IFERROR(B39/C39,0) -> 646.02211 | F39: =B39/$C$17 -> 0.2142203 | G39: =RANK(B39,$B$37:$B$39) -> 2
A40: Total | B40: =SUM(B37:B39) -> 229192.47 | C40: =SUM(C37:C39) -> 250 | D40: =SUM(D37:D39) -> 753 | F40: =SUM(F37:F39) -> 1
A43: 5. Product Sales (Most Sold Products)
A44: Product | B44: Revenue | C44: Transactions | D44: Units | E44: Avg Order | F44: % of Revenue | G44: Rank
A45: Laptop | B45: =SUMIFS('Raw Data'!$N$2:$N$251,'Raw Data'!$F$2:$F$251,A45) -> 67499.25 | C45: =COUNTIFS('Raw Data'!$F$2:$F$251,A45) -> 24 | D45: =SUMIFS('Raw Data'!$H$2:$H$251,'Raw Data'!$F$2:$F$251,A45) -> 75 | E45: =IFERROR(B45/C45,0) -> 2812.4688 | F45: =B45/$C$17 -> 0.29450902 | G45: =RANK(B45,$B$45:$B$54) -> 1
A46: Smartphone | B46: =SUMIFS('Raw Data'!$N$2:$N$251,'Raw Data'!$F$2:$F$251,A46) -> 67199.04 | C46: =COUNTIFS('Raw Data'!$F$2:$F$251,A46) -> 31 | D46: =SUMIFS('Raw Data'!$H$2:$H$251,'Raw Data'!$F$2:$F$251,A46) -> 96 | E46: =IFERROR(B46/C46,0) -> 2167.711 | F46: =B46/$C$17 -> 0.29319916 | G46: =RANK(B46,$B$45:$B$54) -> 2
A47: Desk | B47: =SUMIFS('Raw Data'!$N$2:$N$251,'Raw Data'!$F$2:$F$251,A47) -> 23399.22 | C47: =COUNTIFS('Raw Data'!$F$2:$F$251,A47) -> 26 | D47: =SUMIFS('Raw Data'!$H$2:$H$251,'Raw Data'!$F$2:$F$251,A47) -> 78 | E47: =IFERROR(B47/C47,0) -> 899.97 | F47: =B47/$C$17 -> 0.10209419 | G47: =RANK(B47,$B$45:$B$54) -> 3
A48: Monitor | B48: =SUMIFS('Raw Data'!$N$2:$N$251,'Raw Data'!$F$2:$F$251,A48) -> 21999.12 | C48: =COUNTIFS('Raw Data'!$F$2:$F$251,A48) -> 26 | D48: =SUMIFS('Raw Data'!$H$2:$H$251,'Raw Data'!$F$2:$F$251,A48) -> 88 | E48: =IFERROR(B48/C48,0) -> 846.12 | F48: =B48/$C$17 -> 0.095985352 | G48: =RANK(B48,$B$45:$B$54) -> 4
A49: Bookshelf | B49: =SUMIFS('Raw Data'!$N$2:$N$251,'Raw Data'!$F$2:$F$251,A49) -> 15298.98 | C49: =COUNTIFS('Raw Data'!$F$2:$F$251,A49) -> 35 | D49: =SUMIFS('Raw Data'!$H$2:$H$251,'Raw Data'!$F$2:$F$251,A49) -> 102 | E49: =IFERROR(B49/C49,0) -> 437.11371 | F49: =B49/$C$17 -> 0.066751669 | G49: =RANK(B49,$B$45:$B$54) -> 5
A50: Office Chair | B50: =SUMIFS('Raw Data'!$N$2:$N$251,'Raw Data'!$F$2:$F$251,A50) -> 10399.48 | C50: =COUNTIFS('Raw Data'!$F$2:$F$251,A50) -> 15 | D50: =SUMIFS('Raw Data'!$H$2:$H$251,'Raw Data'!$F$2:$F$251,A50) -> 52 | E50: =IFERROR(B50/C50,0) -> 693.29867 | F50: =B50/$C$17 -> 0.04537444 | G50: =RANK(B50,$B$45:$B$54) -> 6
A51: Keyboard | B51: =SUMIFS('Raw Data'!$N$2:$N$251,'Raw Data'!$F$2:$F$251,A51) -> 8009.11 | C51: =COUNTIFS('Raw Data'!$F$2:$F$251,A51) -> 34 | D51: =SUMIFS('Raw Data'!$H$2:$H$251,'Raw Data'!$F$2:$F$251,A51) -> 89 | E51: =IFERROR(B51/C51,0) -> 235.56206 | F51: =B51/$C$17 -> 0.034944909 | G51: =RANK(B51,$B$45:$B$54) -> 7
A52: Headphones | B52: =SUMIFS('Raw Data'!$N$2:$N$251,'Raw Data'!$F$2:$F$251,A52) -> 7049.53 | C52: =COUNTIFS('Raw Data'!$F$2:$F$251,A52) -> 16 | D52: =SUMIFS('Raw Data'!$H$2:$H$251,'Raw Data'!$F$2:$F$251,A52) -> 47 | E52: =IFERROR(B52/C52,0) -> 440.59562 | F52: =B52/$C$17 -> 0.030758122 | G52: =RANK(B52,$B$45:$B$54) -> 8
A53: Blender | B53: =SUMIFS('Raw Data'!$N$2:$N$251,'Raw Data'!$F$2:$F$251,A53) -> 5219.13 | C53: =COUNTIFS('Raw Data'!$F$2:$F$251,A53) -> 29 | D53: =SUMIFS('Raw Data'!$H$2:$H$251,'Raw Data'!$F$2:$F$251,A53) -> 87 | E53: =IFERROR(B53/C53,0) -> 179.97 | F53: =B53/$C$17 -> 0.022771821 | G53: =RANK(B53,$B$45:$B$54) -> 9
A54: Coffee Maker | B54: =SUMIFS('Raw Data'!$N$2:$N$251,'Raw Data'!$F$2:$F$251,A54) -> 3119.61 | C54: =COUNTIFS('Raw Data'!$F$2:$F$251,A54) -> 14 | D54: =SUMIFS('Raw Data'!$H$2:$H$251,'Raw Data'!$F$2:$F$251,A54) -> 39 | E54: =IFERROR(B54/C54,0) -> 222.82929 | F54: =B54/$C$17 -> 0.013611311 | G54: =RANK(B54,$B$45:$B$54) -> 10
A55: Total | B55: =SUM(B45:B54) -> 229192.47 | C55: =SUM(C45:C54) -> 250 | D55: =SUM(D45:D54) -> 753 | F55: =SUM(F45:F54) -> 1
A58: 6. Payment Method
A59: Payment Method | B59: Revenue | C59: Transactions | D59: Units | E59: Avg Order | F59: % of Revenue | G59: Rank
A60: Cash | B60: =SUMIFS('Raw Data'!$N$2:$N$251,'Raw Data'!$J$2:$J$251,A60) -> 57427.79 | C60: =COUNTIFS('Raw Data'!$J$2:$J$251,A60) -> 76 | D60: =SUMIFS('Raw Data'!$H$2:$H$251,'Raw Data'!$J$2:$J$251,A60) -> 221 | E60: =IFERROR(B60/C60,0) -> 755.62882 | F60: =B60/$C$17 -> 0.25056578 | G60: =RANK(B60,$B$60:$B$63) -> 3
A61: Credit Card | B61: =SUMIFS('Raw Data'!$N$2:$N$251,'Raw Data'!$J$2:$J$251,A61) -> 61447.96 | C61: =COUNTIFS('Raw Data'!$J$2:$J$251,A61) -> 68 | D61: =SUMIFS('Raw Data'!$H$2:$H$251,'Raw Data'!$J$2:$J$251,A61) -> 204 | E61: =IFERROR(B61/C61,0) -> 903.64647 | F61: =B61/$C$17 -> 0.26810636 | G61: =RANK(B61,$B$60:$B$63) -> 1
A62: Debit Card | B62: =SUMIFS('Raw Data'!$N$2:$N$251,'Raw Data'!$J$2:$J$251,A62) -> 52118.31 | C62: =COUNTIFS('Raw Data'!$J$2:$J$251,A62) -> 54 | D62: =SUMIFS('Raw Data'!$H$2:$H$251,'Raw Data'!$J$2:$J$251,A62) -> 169 | E62: =IFERROR(B62/C62,0) -> 965.15389 | F62: =B62/$C$17 -> 0.22739975 | G62: =RANK(B62,$B$60:$B$63) -> 4
A63: PayPal | B63: =SUMIFS('Raw Data'!$N$2:$N$251,'Raw Data'!$J$2:$J$251,A63) -> 58198.41 | C63: =COUNTIFS('Raw Data'!$J$2:$J$251,A63) -> 52 | D63: =SUMIFS('Raw Data'!$H$2:$H$251,'Raw Data'!$J$2:$J$251,A63) -> 159 | E63: =IFERROR(B63/C63,0) -> 1119.2002 | F63: =B63/$C$17 -> 0.25392811 | G63: =RANK(B63,$B$60:$B$63) -> 2
A64: Total | B64: =SUM(B60:B63) -> 229192.47 | C64: =SUM(C60:C63) -> 250 | D64: =SUM(D60:D63) -> 753 | F64: =SUM(F60:F63) -> 1
A65: 7. Customer Segment
A66: Segment | B66: Revenue | C66: Transactions | D66: Units | E66: Avg Order | F66: % of Revenue | G66: Rank
A67: Basic | B67: =SUMIFS('Raw Data'!$N$2:$N$251,'Raw Data'!$L$2:$L$251,A67) -> 62177.81 | C67: =COUNTIFS('Raw Data'!$L$2:$L$251,A67) -> 74 | D67: =SUMIFS('Raw Data'!$H$2:$H$251,'Raw Data'!$L$2:$L$251,A67) -> 219 | E67: =IFERROR(B67/C67,0) -> 840.24068 | F67: =B67/$C$17 -> 0.27129081 | G67: =RANK(B67,$B$67:$B$69) -> 3
A68: Standard | B68: =SUMIFS('Raw Data'!$N$2:$N$251,'Raw Data'!$L$2:$L$251,A68) -> 82357.54 | C68: =COUNTIFS('Raw Data'!$L$2:$L$251,A68) -> 81 | D68: =SUMIFS('Raw Data'!$H$2:$H$251,'Raw Data'!$L$2:$L$251,A68) -> 246 | E68: =IFERROR(B68/C68,0) -> 1016.7598 | F68: =B68/$C$17 -> 0.3593379 | G68: =RANK(B68,$B$67:$B$69) -> 2
A69: Premium | B69: =SUMIFS('Raw Data'!$N$2:$N$251,'Raw Data'!$L$2:$L$251,A69) -> 84657.12 | C69: =COUNTIFS('Raw Data'!$L$2:$L$251,A69) -> 95 | D69: =SUMIFS('Raw Data'!$H$2:$H$251,'Raw Data'!$L$2:$L$251,A69) -> 288 | E69: =IFERROR(B69/C69,0) -> 891.12758 | F69: =B69/$C$17 -> 0.3693713 | G69: =RANK(B69,$B$67:$B$69) -> 1
A70: Total | B70: =SUM(B67:B69) -> 229192.47 | C70: =SUM(C67:C69) -> 250 | D70: =SUM(D67:D69) -> 753 | F70: =SUM(F67:F69) -> 1
A72: 8. Monthly Revenue Trend (EOMONTH)
A73: Month Start | B73: Month End (EOMONTH) | C73: Revenue | D73: Transactions | E73: MoM Growth % | F73: Trend
A74: =DATE(YEAR(C9),MONTH(C9),1) -> 45383 | B74: =EOMONTH(A74,0) -> 45412 | C74: =SUMIFS('Raw Data'!$N$2:$N$251,'Raw Data'!$O$2:$O$251,A74) -> 20919.33 | D74: =COUNTIFS('Raw Data'!$O$2:$O$251,A74) -> 21 | E74: ="" | F74: =""
A75: =EOMONTH(A74,0)+1 -> 45413 | B75: =EOMONTH(A75,0) -> 45443 | C75: =SUMIFS('Raw Data'!$N$2:$N$251,'Raw Data'!$O$2:$O$251,A75) -> 17039.35 | D75: =COUNTIFS('Raw Data'!$O$2:$O$251,A75) -> 19 | E75: =IFERROR(C75/C74-1,0) -> -0.18547344 | F75: =C75-C74 -> -3879.98
A76: =EOMONTH(A75,0)+1 -> 45444 | B76: =EOMONTH(A76,0) -> 45473 | C76: =SUMIFS('Raw Data'!$N$2:$N$251,'Raw Data'!$O$2:$O$251,A76) -> 19299.45 | D76: =COUNTIFS('Raw Data'!$O$2:$O$251,A76) -> 19 | E76: =IFERROR(C76/C75-1,0) -> 0.13264004 | F76: =C76-C75 -> 2260.1
A77: =EOMONTH(A76,0)+1 -> 45474 | B77: =EOMONTH(A77,0) -> 45504 | C77: =SUMIFS('Raw Data'!$N$2:$N$251,'Raw Data'!$O$2:$O$251,A77) -> 18479.4 | D77: =COUNTIFS('Raw Data'!$O$2:$O$251,A77) -> 24 | E77: =IFERROR(C77/C76-1,0) -> -0.042490848 | F77: =C77-C76 -> -820.05
A78: =EOMONTH(A77,0)+1 -> 45505 | B78: =EOMONTH(A78,0) -> 45535 | C78: =SUMIFS('Raw Data'!$N$2:$N$251,'Raw Data'!$O$2:$O$251,A78) -> 15759.43 | D78: =COUNTIFS('Raw Data'!$O$2:$O$251,A78) -> 18 | E78: =IFERROR(C78/C77-1,0) -> -0.1471893 | F78: =C78-C77 -> -2719.97
A79: =EOMONTH(A78,0)+1 -> 45536 | B79: =EOMONTH(A79,0) -> 45565 | C79: =SUMIFS('Raw Data'!$N$2:$N$251,'Raw Data'!$O$2:$O$251,A79) -> 12989.51 | D79: =COUNTIFS('Raw Data'!$O$2:$O$251,A79) -> 19 | E79: =IFERROR(C79/C78-1,0) -> -0.1757627 | F79: =C79-C78 -> -2769.92
A80: =EOMONTH(A79,0)+1 -> 45566 | B80: =EOMONTH(A80,0) -> 45596 | C80: =SUMIFS('Raw Data'!$N$2:$N$251,'Raw Data'!$O$2:$O$251,A80) -> 20609.52 | D80: =COUNTIFS('Raw Data'!$O$2:$O$251,A80) -> 16 | E80: =IFERROR(C80/C79-1,0) -> 0.58662798 | F80: =C80-C79 -> 7620.01
A81: =EOMONTH(A80,0)+1 -> 45597 | B81: =EOMONTH(A81,0) -> 45626 | C81: =SUMIFS('Raw Data'!$N$2:$N$251,'Raw Data'!$O$2:$O$251,A81) -> 12309.44 | D81: =COUNTIFS('Raw Data'!$O$2:$O$251,A81) -> 17 | E81: =IFERROR(C81/C80-1,0) -> -0.40273039 | F81: =C81-C80 -> -8300.08
A82: =EOMONTH(A81,0)+1 -> 45627 | B82: =EOMONTH(A82,0) -> 45657 | C82: =SUMIFS('Raw Data'!$N$2:$N$251,'Raw Data'!$O$2:$O$251,A82) -> 23039.3 | D82: =COUNTIFS('Raw Data'!$O$2:$O$251,A82) -> 25 | E82: =IFERROR(C82/C81-1,0) -> 0.87167735 | F82: =C82-C81 -> 10729.86
A83: =EOMONTH(A82,0)+1 -> 45658 | B83: =EOMONTH(A83,0) -> 45688 | C83: =SUMIFS('Raw Data'!$N$2:$N$251,'Raw Data'!$O$2:$O$251,A83) -> 25799.15 | D83: =COUNTIFS('Raw Data'!$O$2:$O$251,A83) -> 26 | E83: =IFERROR(C83/C82-1,0) -> 0.1197888 | F83: =C83-C82 -> 2759.85
A84: =EOMONTH(A83,0)+1 -> 45689 | B84: =EOMONTH(A84,0) -> 45716 | C84: =SUMIFS('Raw Data'!$N$2:$N$251,'Raw Data'!$O$2:$O$251,A84) -> 16069.38 | D84: =COUNTIFS('Raw Data'!$O$2:$O$251,A84) -> 20 | E84: =IFERROR(C84/C83-1,0) -> -0.37713529 | F84: =C84-C83 -> -9729.77
A85: =EOMONTH(A84,0)+1 -> 45717 | B85: =EOMONTH(A85,0) -> 45747 | C85: =SUMIFS('Raw Data'!$N$2:$N$251,'Raw Data'!$O$2:$O$251,A85) -> 19899.38 | D85: =COUNTIFS('Raw Data'!$O$2:$O$251,A85) -> 19 | E85: =IFERROR(C85/C84-1,0) -> 0.23834149 | F85: =C85-C84 -> 3830
A86: =EOMONTH(A85,0)+1 -> 45748 | B86: =EOMONTH(A86,0) -> 45777 | C86: =SUMIFS('Raw Data'!$N$2:$N$251,'Raw Data'!$O$2:$O$251,A86) -> 6979.83 | D86: =COUNTIFS('Raw Data'!$O$2:$O$251,A86) -> 7 | E86: =IFERROR(C86/C85-1,0) -> -0.64924385 | F86: =C86-C85 -> -12919.55
A89: 9. Customer GroupBy - High-Value Customers (formulas) + Abbreviations (TEXT functions)
A90: Customer_ID | B90: Customer Name | C90: Revenue | D90: Orders | E90: Avg Order | F90: Rank | G90: Tier | H90: Repeat? | I90: Initials | J90: Short Code | K90: Bought Electronics | L90: Bought Furniture | M90: Match (both) | N90: Rank Key
A91: CUST001 | B91: =INDEX('Raw Data'!$D$2:$D$251,MATCH(A91,'Raw Data'!$C$2:$C$251,0)) -> John Smith | C91: =SUMIFS('Raw Data'!$N$2:$N$251,'Raw Data'!$C$2:$C$251,A91) -> 599.96 | D91: =COUNTIFS('Raw Data'!$C$2:$C$251,A91) -> 1 | E91: =C91/D91 -> 599.96 | F91: =RANK(N91,$N$91:$N$140) -> 47 | G91: =IF(F91<=10,"High Value",IF(F91<=25,"Mid Value","Regular")) -> Regular | H91: =IF(D91>1,"Repeat","One-time") -> One-time | I91: =UPPER(LEFT(B91,1)&MID(B91,FIND(" ",B91)+1,1)) -> JS | J91: =UPPER(LEFT(B91,3))&"-"&RIGHT(A91,3) -> JOH-001 | K91: =IF(COUNTIFS('Raw Data'!$C$2:$C$251,A91,'Raw Data'!$G$2:$G$251,"Electronics")>0,B91,"") | L91: =IF(COUNTIFS('Raw Data'!$C$2:$C$251,A91,'Raw Data'!$G$2:$G$251,"Furniture")>0,B91,"") -> John Smith | M91: =IF(K91="","",IFERROR(INDEX($L$91:$L$140,MATCH(K91,$L$91:$L$140,0)),"")) | N91: =C91+ROW()/1000000 -> 599.96009
A92: CUST002 | B92: =INDEX('Raw Data'!$D$2:$D$251,MATCH(A92,'Raw Data'!$C$2:$C$251,0)) -> Emma Wilson | C92: =SUMIFS('Raw Data'!$N$2:$N$251,'Raw Data'!$C$2:$C$251,A92) -> 1229.88 | D92: =COUNTIFS('Raw Data'!$C$2:$C$251,A92) -> 5 | E92: =C92/D92 -> 245.976 | F92: =RANK(N92,$N$91:$N$140) -> 44 | G92: =IF(F92<=10,"High Value",IF(F92<=25,"Mid Value","Regular")) -> Regular | H92: =IF(D92>1,"Repeat","One-time") -> Repeat | I92: =UPPER(LEFT(B92,1)&MID(B92,FIND(" ",B92)+1,1)) -> EW | J92: =UPPER(LEFT(B92,3))&"-"&RIGHT(A92,3) -> EMM-002 | K92: =IF(COUNTIFS('Raw Data'!$C$2:$C$251,A92,'Raw Data'!$G$2:$G$251,"Electronics")>0,B92,"") -> Emma Wilson | L92: =IF(COUNTIFS('Raw Data'!$C$2:$C$251,A92,'Raw Data'!$G$2:$G$251,"Furniture")>0,B92,"") -> Emma Wilson | M92: =IF(K92="","",IFERROR(INDEX($L$91:$L$140,MATCH(K92,$L$91:$L$140,0)),"")) -> Emma Wilson | N92: =C92+ROW()/1000000 -> 1229.8801
A93: CUST003 | B93: =INDEX('Raw Data'!$D$2:$D$251,MATCH(A93,'Raw Data'!$C$2:$C$251,0)) -> Michael Brown | C93: =SUMIFS('Raw Data'!$N$2:$N$251,'Raw Data'!$C$2:$C$251,A93) -> 6169.74 | D93: =COUNTIFS('Raw Data'!$C$2:$C$251,A93) -> 9 | E93: =C93/D93 -> 685.52667 | F93: =RANK(N93,$N$91:$N$140) -> 14 | G93: =IF(F93<=10,"High Value",IF(F93<=25,"Mid Value","Regular")) -> Mid Value | H93: =IF(D93>1,"Repeat","One-time") -> Repeat | I93: =UPPER(LEFT(B93,1)&MID(B93,FIND(" ",B93)+1,1)) -> MB | J93: =UPPER(LEFT(B93,3))&"-"&RIGHT(A93,3) -> MIC-003 | K93: =IF(COUNTIFS('Raw Data'!$C$2:$C$251,A93,'Raw Data'!$G$2:$G$251,"Electronics")>0,B93,"") -> Michael Brown | L93: =IF(COUNTIFS('Raw Data'!$C$2:$C$251,A93,'Raw Data'!$G$2:$G$251,"Furniture")>0,B93,"") -> Michael Brown | M93: =IF(K93="","",IFERROR(INDEX($L$91:$L$140,MATCH(K93,$L$91:$L$140,0)),"")) -> Michael Brown | N93: =C93+ROW()/1000000 -> 6169.7401
A94: CUST004 | B94: =INDEX('Raw Data'!$D$2:$D$251,MATCH(A94,'Raw Data'!$C$2:$C$251,0)) -> Sarah Davis | C94: =SUMIFS('Raw Data'!$N$2:$N$251,'Raw Data'!$C$2:$C$251,A94) -> 5499.81 | D94: =COUNTIFS('Raw Data'!$C$2:$C$251,A94) -> 5 | E94: =C94/D94 -> 1099.962 | F94: =RANK(N94,$N$91:$N$140) -> 19 | G94: =IF(F94<=10,"High Value",IF(F94<=25,"Mid Value","Regular")) -> Mid Value | H94: =IF(D94>1,"Repeat","One-time") -> Repeat | I94: =UPPER(LEFT(B94,1)&MID(B94,FIND(" ",B94)+1,1)) -> SD | J94: =UPPER(LEFT(B94,3))&"-"&RIGHT(A94,3) -> SAR-004 | K94: =IF(COUNTIFS('Raw Data'!$C$2:$C$251,A94,'Raw Data'!$G$2:$G$251,"Electronics")>0,B94,"") -> Sarah Davis | L94: =IF(COUNTIFS('Raw Data'!$C$2:$C$251,A94,'Raw Data'!$G$2:$G$251,"Furniture")>0,B94,"") -> Sarah Davis | M94: =IF(K94="","",IFERROR(INDEX($L$91:$L$140,MATCH(K94,$L$91:$L$140,0)),"")) -> Sarah Davis | N94: =C94+ROW()/1000000 -> 5499.8101
A95: CUST005 | B95: =INDEX('Raw Data'!$D$2:$D$251,MATCH(A95,'Raw Data'!$C$2:$C$251,0)) -> James Johnson | C95: =SUMIFS('Raw Data'!$N$2:$N$251,'Raw Data'!$C$2:$C$251,A95) -> 179.97 | D95: =COUNTIFS('Raw Data'!$C$2:$C$251,A95) -> 1 | E95: =C95/D95 -> 179.97 | F95: =RANK(N95,$N$91:$N$140) -> 50 | G95: =IF(F95<=10,"High Value",IF(F95<=25,"Mid Value","Regular")) -> Regular | H95: =IF(D95>1,"Repeat","One-time") -> One-time | I95: =UPPER(LEFT(B95,1)&MID(B95,FIND(" ",B95)+1,1)) -> JJ | J95: =UPPER(LEFT(B95,3))&"-"&RIGHT(A95,3) -> JAM-005 | K95: =IF(COUNTIFS('Raw Data'!$C$2:$C$251,A95,'Raw Data'!$G$2:$G$251,"Electronics")>0,B95,"") | L95: =IF(COUNTIFS('Raw Data'!$C$2:$C$251,A95,'Raw Data'!$G$2:$G$251,"Furniture")>0,B95,"") | M95: =IF(K95="","",IFERROR(INDEX($L$91:$L$140,MATCH(K95,$L$91:$L$140,0)),"")) | N95: =C95+ROW()/1000000 -> 179.97009
A96: CUST006 | B96: =INDEX('Raw Data'!$D$2:$D$251,MATCH(A96,'Raw Data'!$C$2:$C$251,0)) -> Lisa Anderson | C96: =SUMIFS('Raw Data'!$N$2:$N$251,'Raw Data'!$C$2:$C$251,A96) -> 2039.8 | D96: =COUNTIFS('Raw Data'!$C$2:$C$251,A96) -> 5 | E96: =C96/D96 -> 407.96 | F96: =RANK(N96,$N$91:$N$140) -> 36 | G96: =IF(F96<=10,"High Value",IF(F96<=25,"Mid Value","Regular")) -> Regular | H96: =IF(D96>1,"Repeat","One-time") -> Repeat | I96: =UPPER(LEFT(B96,1)&MID(B96,FIND(" ",B96)+1,1)) -> LA | J96: =UPPER(LEFT(B96,3))&"-"&RIGHT(A96,3) -> LIS-006 | K96: =IF(COUNTIFS('Raw Data'!$C$2:$C$251,A96,'Raw Data'!$G$2:$G$251,"Electronics")>0,B96,"") -> Lisa Anderson | L96: =IF(COUNTIFS('Raw Data'!$C$2:$C$251,A96,'Raw Data'!$G$2:$G$251,"Furniture")>0,B96,"") -> Lisa Anderson | M96: =IF(K96="","",IFERROR(INDEX($L$91:$L$140,MATCH(K96,$L$91:$L$140,0)),"")) -> Lisa Anderson | N96: =C96+ROW()/1000000 -> 2039.8001
A97: CUST007 | B97: =INDEX('Raw Data'!$D$2:$D$251,MATCH(A97,'Raw Data'!$C$2:$C$251,0)) -> David Martinez | C97: =SUMIFS('Raw Data'!$N$2:$N$251,'Raw Data'!$C$2:$C$251,A97) -> 1809.84 | D97: =COUNTIFS('Raw Data'!$C$2:$C$251,A97) -> 6 | E97: =C97/D97 -> 301.64 | F97: =RANK(N97,$N$91:$N$140) -> 39 | G97: =IF(F97<=10,"High Value",IF(F97<=25,"Mid Value","Regular")) -> Regular | H97: =IF(D97>1,"Repeat","One-time") -> Repeat | I97: =UPPER(LEFT(B97,1)&MID(B97,FIND(" ",B97)+1,1)) -> DM | J97: =UPPER(LEFT(B97,3))&"-"&RIGHT(A97,3) -> DAV-007 | K97: =IF(COUNTIFS('Raw Data'!$C$2:$C$251,A97,'Raw Data'!$G$2:$G$251,"Electronics")>0,B97,"") -> David Martinez | L97: =IF(COUNTIFS('Raw Data'!$C$2:$C$251,A97,'Raw Data'!$G$2:$G$251,"Furniture")>0,B97,"") -> David Martinez | M97: =IF(K97="","",IFERROR(INDEX($L$91:$L$140,MATCH(K97,$L$91:$L$140,0)),"")) -> David Martinez | N97: =C97+ROW()/1000000 -> 1809.8401
A98: CUST008 | B98: =INDEX('Raw Data'!$D$2:$D$251,MATCH(A98,'Raw Data'!$C$2:$C$251,0)) -> Jennifer Taylor | C98: =SUMIFS('Raw Data'!$N$2:$N$251,'Raw Data'!$C$2:$C$251,A98) -> 4739.85 | D98: =COUNTIFS('Raw Data'!$C$2:$C$251,A98) -> 4 | E98: =C98/D98 -> 1184.9625 | F98: =RANK(N98,$N$91:$N$140) -> 24 | G98: =IF(F98<=10,"High Value",IF(F98<=25,"Mid Value","Regular")) -> Mid Value | H98: =IF(D98>1,"Repeat","One-time") -> Repeat | I98: =UPPER(LEFT(B98,1)&MID(B98,FIND(" ",B98)+1,1)) -> JT | J98: =UPPER(LEFT(B98,3))&"-"&RIGHT(A98,3) -> JEN-008 | K98: =IF(COUNTIFS('Raw Data'!$C$2:$C$251,A98,'Raw Data'!$G$2:$G$251,"Electronics")>0,B98,"") -> Jennifer Taylor | L98: =IF(COUNTIFS('Raw Data'!$C$2:$C$251,A98,'Raw Data'!$G$2:$G$251,"Furniture")>0,B98,"") -> Jennifer Taylor | M98: =IF(K98="","",IFERROR(INDEX($L$91:$L$140,MATCH(K98,$L$91:$L$140,0)),"")) -> Jennifer Taylor | N98: =C98+ROW()/1000000 -> 4739.8501
A99: CUST009 | B99: =INDEX('Raw Data'!$D$2:$D$251,MATCH(A99,'Raw Data'!$C$2:$C$251,0)) -> Robert Thomas | C99: =SUMIFS('Raw Data'!$N$2:$N$251,'Raw Data'!$C$2:$C$251,A99) -> 3509.9 | D99: =COUNTIFS('Raw Data'!$C$2:$C$251,A99) -> 5 | E99: =C99/D99 -> 701.98 | F99: =RANK(N99,$N$91:$N$140) -> 32 | G99: =IF(F99<=10,"High Value",IF(F99<=25,"Mid Value","Regular")) -> Regular | H99: =IF(D99>1,"Repeat","One-time") -> Repeat | I99: =UPPER(LEFT(B99,1)&MID(B99,FIND(" ",B99)+1,1)) -> RT | J99: =UPPER(LEFT(B99,3))&"-"&RIGHT(A99,3) -> ROB-009 | K99: =IF(COUNTIFS('Raw Data'!$C$2:$C$251,A99,'Raw Data'!$G$2:$G$251,"Electronics")>0,B99,"") -> Robert Thomas | L99: =IF(COUNTIFS('Raw Data'!$C$2:$C$251,A99,'Raw Data'!$G$2:$G$251,"Furniture")>0,B99,"") -> Robert Thomas | M99: =IF(K99="","",IFERROR(INDEX($L$91:$L$140,MATCH(K99,$L$91:$L$140,0)),"")) -> Robert Thomas | N99: =C99+ROW()/1000000 -> 3509.9001
A100: CUST010 | B100: =INDEX('Raw Data'!$D$2:$D$251,MATCH(A100,'Raw Data'!$C$2:$C$251,0)) -> Maria Garcia | C100: =SUMIFS('Raw Data'!$N$2:$N$251,'Raw Data'!$C$2:$C$251,A100) -> 1909.93 | D100: =COUNTIFS('Raw Data'!$C$2:$C$251,A100) -> 4 | E100: =C100/D100 -> 477.4825 | F100: =RANK(N100,$N$91:$N$140) -> 38 | G100: =IF(F100<=10,"High Value",IF(F100<=25,"Mid Value","Regular")) -> Regular | H100: =IF(D100>1,"Repeat","One-time") -> Repeat | I100: =UPPER(LEFT(B100,1)&MID(B100,FIND(" ",B100)+1,1)) -> MG | J100: =UPPER(LEFT(B100,3))&"-"&RIGHT(A100,3) -> MAR-010 | K100: =IF(COUNTIFS('Raw Data'!$C$2:$C$251,A100,'Raw Data'!$G$2:$G$251,"Electronics")>0,B100,"") -> Maria Garcia | L100: =IF(COUNTIFS('Raw Data'!$C$2:$C$251,A100,'Raw Data'!$G$2:$G$251,"Furniture")>0,B100,"") -> Maria Garcia | M100: =IF(K100="","",IFERROR(INDEX($L$91:$L$140,MATCH(K100,$L$91:$L$140,0)),"")) -> Maria Garcia | N100: =C100+ROW()/1000000 -> 1909.9301
A101: CUST011 | B101: =INDEX('Raw Data'!$D$2:$D$251,MATCH(A101,'Raw Data'!$C$2:$C$251,0)) -> William White | C101: =SUMIFS('Raw Data'!$N$2:$N$251,'Raw Data'!$C$2:$C$251,A101) -> 4749.91 | D101: =COUNTIFS('Raw Data'!$C$2:$C$251,A101) -> 3 | E101: =C101/D101 -> 1583.3033 | F101: =RANK(N101,$N$91:$N$140) -> 23 | G101: =IF(F101<=10,"High Value",IF(F101<=25,"Mid Value","Regular")) -> Mid Value | H101: =IF(D101>1,"Repeat","One-time") -> Repeat | I101: =UPPER(LEFT(B101,1)&MID(B101,FIND(" ",B101)+1,1)) -> WW | J101: =UPPER(LEFT(B101,3))&"-"&RIGHT(A101,3) -> WIL-011 | K101: =IF(COUNTIFS('Raw Data'!$C$2:$C$251,A101,'Raw Data'!$G$2:$G$251,"Electronics")>0,B101,"") -> William White | L101: =IF(COUNTIFS('Raw Data'!$C$2:$C$251,A101,'Raw Data'!$G$2:$G$251,"Furniture")>0,B101,"") | M101: =IF(K101="","",IFERROR(INDEX($L$91:$L$140,MATCH(K101,$L$91:$L$140,0)),"")) | N101: =C101+ROW()/1000000 -> 4749.9101
A102: CUST012 | B102: =INDEX('Raw Data'!$D$2:$D$251,MATCH(A102,'Raw Data'!$C$2:$C$251,0)) -> Patricia Moore | C102: =SUMIFS('Raw Data'!$N$2:$N$251,'Raw Data'!$C$2:$C$251,A102) -> 9799.73 | D102: =COUNTIFS('Raw Data'!$C$2:$C$251,A102) -> 8 | E102: =C102/D102 -> 1224.9662 | F102: =RANK(N102,$N$91:$N$140) -> 4 | G102: =IF(F102<=10,"High Value",IF(F102<=25,"Mid Value","Regular")) -> High Value | H102: =IF(D102>1,"Repeat","One-time") -> Repeat | I102: =UPPER(LEFT(B102,1)&MID(B102,FIND(" ",B102)+1,1)) -> PM | J102: =UPPER(LEFT(B102,3))&"-"&RIGHT(A102,3) -> PAT-012 | K102: =IF(COUNTIFS('Raw Data'!$C$2:$C$251,A102,'Raw Data'!$G$2:$G$251,"Electronics")>0,B102,"") -> Patricia Moore | L102: =IF(COUNTIFS('Raw Data'!$C$2:$C$251,A102,'Raw Data'!$G$2:$G$251,"Furniture")>0,B102,"") -> Patricia Moore | M102: =IF(K102="","",IFERROR(INDEX($L$91:$L$140,MATCH(K102,$L$91:$L$140,0)),"")) -> Patricia Moore | N102: =C102+ROW()/1000000 -> 9799.7301
... A140: CUST050 | B140: =INDEX('Raw Data'!$D$2:$D$251,MATCH(A140,'Raw Data'!$C$2:$C$251,0)) -> Julie Foster | C140: =SUMIFS('Raw Data'!$N$2:$N$251,'Raw Data'!$C$2:$C$251,A140) -> 239.96 | D140: =COUNTIFS('Raw Data'!$C$2:$C$251,A140) -> 1 | E140: =C140/D140 -> 239.96 | F140: =RANK(N140,$N$91:$N$140) -> 49 | G140: =IF(F140<=10,"High Value",IF(F140<=25,"Mid Value","Regular")) -> Regular | H140: =IF(D140>1,"Repeat","One-time") -> One-time | I140: =UPPER(LEFT(B140,1)&MID(B140,FIND(" ",B140)+1,1)) -> JF | J140: =UPPER(LEFT(B140,3))&"-"&RIGHT(A140,3) -> JUL-050 | K140: =IF(COUNTIFS('Raw Data'!$C$2:$C$251,A140,'Raw Data'!$G$2:$G$251,"Electronics")>0,B140,"") | L140: =IF(COUNTIFS('Raw Data'!$C$2:$C$251,A140,'Raw Data'!$G$2:$G$251,"Furniture")>0,B140,"") | M140: =IF(K140="","",IFERROR(INDEX($L$91:$L$140,MATCH(K140,$L$91:$L$140,0)),"")) | N140: =C140+ROW()/1000000 -> 239.96014
A143: 10. Top 10 Customers (formula based)
A144: Rank | B144: Customer | C144: Revenue | D144: Orders | E144: Share of Revenue
A145: 1 | B145: =INDEX($B$91:$B$140,MATCH(A145,$F$91:$F$140,0)) -> Mark Carter | C145: =INDEX($C$91:$C$140,MATCH(A145,$F$91:$F$140,0)) -> 15659.65 | D145: =INDEX($D$91:$D$140,MATCH(A145,$F$91:$F$140,0)) -> 12 | E145: =C145/$C$17 -> 0.068325325
A146: 2 | B146: =INDEX($B$91:$B$140,MATCH(A146,$F$91:$F$140,0)) -> Edward Mitchell | C146: =INDEX($C$91:$C$140,MATCH(A146,$F$91:$F$140,0)) -> 11919.77 | D146: =INDEX($D$91:$D$140,MATCH(A146,$F$91:$F$140,0)) -> 6 | E146: =C146/$C$17 -> 0.052007686
A147: 3 | B147: =INDEX($B$91:$B$140,MATCH(A147,$F$91:$F$140,0)) -> Barbara Young | C147: =INDEX($C$91:$C$140,MATCH(A147,$F$91:$F$140,0)) -> 10649.8 | D147: =INDEX($D$91:$D$140,MATCH(A147,$F$91:$F$140,0)) -> 5 | E147: =C147/$C$17 -> 0.046466623
A148: 4 | B148: =INDEX($B$91:$B$140,MATCH(A148,$F$91:$F$140,0)) -> Patricia Moore | C148: =INDEX($C$91:$C$140,MATCH(A148,$F$91:$F$140,0)) -> 9799.73 | D148: =INDEX($D$91:$D$140,MATCH(A148,$F$91:$F$140,0)) -> 8 | E148: =C148/$C$17 -> 0.042757644
A149: 5 | B149: =INDEX($B$91:$B$140,MATCH(A149,$F$91:$F$140,0)) -> Paul Baker | C149: =INDEX($C$91:$C$140,MATCH(A149,$F$91:$F$140,0)) -> 8309.74 | D149: =INDEX($D$91:$D$140,MATCH(A149,$F$91:$F$140,0)) -> 8 | E149: =C149/$C$17 -> 0.036256601
A150: 6 | B150: =INDEX($B$91:$B$140,MATCH(A150,$F$91:$F$140,0)) -> Dorothy Nelson | C150: =INDEX($C$91:$C$140,MATCH(A150,$F$91:$F$140,0)) -> 8269.79 | D150: =INDEX($D$91:$D$140,MATCH(A150,$F$91:$F$140,0)) -> 6 | E150: =C150/$C$17 -> 0.036082294
A151: 7 | B151: =INDEX($B$91:$B$140,MATCH(A151,$F$91:$F$140,0)) -> Karen Hill | C151: =INDEX($C$91:$C$140,MATCH(A151,$F$91:$F$140,0)) -> 8009.77 | D151: =INDEX($D$91:$D$140,MATCH(A151,$F$91:$F$140,0)) -> 8 | E151: =C151/$C$17 -> 0.034947789
A152: 8 | B152: =INDEX($B$91:$B$140,MATCH(A152,$F$91:$F$140,0)) -> Daniel King | C152: =INDEX($C$91:$C$140,MATCH(A152,$F$91:$F$140,0)) -> 7309.8 | D152: =INDEX($D$91:$D$140,MATCH(A152,$F$91:$F$140,0)) -> 7 | E152: =C152/$C$17 -> 0.031893718
...

Sheet What-If & Regression
A1: What-If Analysis and Linear Regression
A3: A. Scenario Manager (scenario table - choose scenario in C5)
A5: Active scenario (1-3) | C5: 2
A7: Input | B7: Pessimistic (1) | C7: Base (2) | D7: Optimistic (3) | E7: ACTIVE
A8: Sales volume change % | B8: -0.1 | C8: 0 | D8: 0.15 | E8: =CHOOSE($C$5,B8,C8,D8) -> 0
A9: Price change % | B9: -0.05 | C9: 0 | D9: 0.05 | E9: =CHOOSE($C$5,B9,C9,D9) -> 0
A10: Cost of goods (% of revenue) | B10: 0.7 | C10: 0.65 | D10: 0.6 | E10: =CHOOSE($C$5,B10,C10,D10) -> 0.65
A11: Operating expenses ($) | B11: 60000 | C11: 55000 | D11: 50000 | E11: =CHOOSE($C$5,B11,C11,D11) -> 55000
A13: Current Revenue (from data) | E13: =Analysis!C17 -> 229192.47
A14: Projected Revenue | E14: =E13*(1+E8)*(1+E9) -> 229192.47
A15: Cost of goods | E15: =E14*E10 -> 148975.11
A16: Operating expenses | E16: =E11 -> 55000
A17: Projected Profit | E17: =E14-E15-E16 -> 25217.365
A18: Profit margin | E18: =IFERROR(E17/E14,0) -> 0.11002702
A21: Scenario | B21: Revenue | C21: Profit
A22: Pessimistic | B22: =$E$13*(1+B8)*(1+B9) -> 195959.56 | C22: =B22-B22*B10-B11 -> -1212.1314
A23: Base | B23: =$E$13*(1+C8)*(1+C9) -> 229192.47 | C23: =B23-B23*C10-C11 -> 25217.365
A24: Optimistic | B24: =$E$13*(1+D8)*(1+D9) -> 276749.91 | C24: =B24-B24*D10-D11 -> 60699.963
A27: B. Goal Seek (solved with a formula - result is exact)
A29: Target total revenue ($) | C29: 275000
A30: Current total revenue | C30: =Analysis!C17 -> 229192.47
A31: Required increase in sales volume | C31: =C29/C30-1 -> 0.1998649
A32: Required price (avg order) if volume fixed | C32: =Analysis!C19*C29/C30 -> 1100
A33: Check: revenue after change | C33: =C30*(1+C31) -> 275000
A36: C. Linear Regression: Monthly Revenue vs Month number (SLOPE / INTERCEPT / RSQ / LINEST)
A37: Month # | B37: Month | C37: Revenue (Y) | D37: Predicted | E37: Residual
A38: 1 | B38: =Analysis!A74 -> 45383 | C38: =Analysis!C74 -> 20919.33 | D38: =$C$52+$C$51*A38 -> 17640.446 | E38: =C38-D38 -> 3278.8842
A39: 2 | B39: =Analysis!A75 -> 45413 | C39: =Analysis!C75 -> 17039.35 | D39: =$C$52+$C$51*A39 -> 17799.95 | E39: =C39-D39 -> -760.60017
A40: 3 | B40: =Analysis!A76 -> 45444 | C40: =Analysis!C76 -> 19299.45 | D40: =$C$52+$C$51*A40 -> 17959.455 | E40: =C40-D40 -> 1339.9954
A41: 4 | B41: =Analysis!A77 -> 45474 | C41: =Analysis!C77 -> 18479.4 | D41: =$C$52+$C$51*A41 -> 18118.959 | E41: =C41-D41 -> 360.44101
A42: 5 | B42: =Analysis!A78 -> 45505 | C42: =Analysis!C78 -> 15759.43 | D42: =$C$52+$C$51*A42 -> 18278.463 | E42: =C42-D42 -> -2519.0334
A43: 6 | B43: =Analysis!A79 -> 45536 | C43: =Analysis!C79 -> 12989.51 | D43: =$C$52+$C$51*A43 -> 18437.968 | E43: =C43-D43 -> -5448.4578
A44: 7 | B44: =Analysis!A80 -> 45566 | C44: =Analysis!C80 -> 20609.52 | D44: =$C$52+$C$51*A44 -> 18597.472 | E44: =C44-D44 -> 2012.0478
A45: 8 | B45: =Analysis!A81 -> 45597 | C45: =Analysis!C81 -> 12309.44 | D45: =$C$52+$C$51*A45 -> 18756.977 | E45: =C45-D45 -> -6447.5366
A46: 9 | B46: =Analysis!A82 -> 45627 | C46: =Analysis!C82 -> 23039.3 | D46: =$C$52+$C$51*A46 -> 18916.481 | E46: =C46-D46 -> 4122.819
A47: 10 | B47: =Analysis!A83 -> 45658 | C47: =Analysis!C83 -> 25799.15 | D47: =$C$52+$C$51*A47 -> 19075.985 | E47: =C47-D47 -> 6723.1646
A48: 11 | B48: =Analysis!A84 -> 45689 | C48: =Analysis!C84 -> 16069.38 | D48: =$C$52+$C$51*A48 -> 19235.49 | E48: =C48-D48 -> -3166.1098
A49: 12 | B49: =Analysis!A85 -> 45717 | C49: =Analysis!C85 -> 19899.38 | D49: =$C$52+$C$51*A49 -> 19394.994 | E49: =C49-D49 -> 504.38577
A51: Slope (revenue change per month) | C51: =SLOPE(C38:C49,A38:A49) -> 159.50441
A52: Intercept | C52: =INTERCEPT(C38:C49,A38:A49) -> 17480.941
A53: R-squared | C53: =RSQ(C38:C49,A38:A49) -> 0.021273185
A54: Std error of estimate | C54: =STEYX(C38:C49,A38:A49) -> 4091.2421
A55: Correlation (r) | C55: =CORREL(A38:A49,C38:C49) -> 0.1458533
A56: Forecast - Month 13 | C56: =C52+C51*13 -> 19554.499
A57: Forecast - Month 14 | C57: =C52+C51*14 -> 19714.003

Sheet Visualizations
A1: Visualizations - Additional Charts

Sheet Dashboard
A1: DATA INTELLIGENCE DASHBOARD | Q1: ="Report date: "&TEXT(Analysis!C7,"dd-mmm-yyyy") -> Report date: 15-Oct-2026
A3: ="Customer transaction analysis | Data period: "&TEXT(Analysis!C9,"dd-mmm-yyyy")&" to "&TEXT(Analysis!C10,"dd-mmm-yyyy") -> Customer transaction analysis | Data period: 11-Apr-2024 to 11-Apr-2025
A4: FILTERS > | D4: ="Region: "&Analysis!C5 -> Region: All | G4: ="Category: "&Analysis!C6 -> Category: All
A7: TOTAL REVENUE | E7: TRANSACTIONS | I7: AVG ORDER VALUE | M7: CUSTOMERS | Q7: FILTERED REVENUE | U7: TOP REGION
A8: =Analysis!C17 -> 229192.47 | E8: =Analysis!C18 -> 250 | I8: =Analysis!C19 -> 916.76988 | M8: =Analysis!C21 -> 50 | Q8: =Analysis!C22 -> 229192.47 | U8: =INDEX(Analysis!A28:A32,MATCH(1,Analysis!G28:G32,0)) -> East
A10: ="from "&Analysis!C18&" orders" -> from 250 orders | E10: ="Units sold: "&TEXT(Analysis!C20,"#,##0") -> Units sold: 753 | I10: per transaction | M10: ="Repeat rate "&TEXT(Analysis!C161,"0%") -> Repeat rate 94% | Q10: ="Selected: "&Analysis!C5&" / "&Analysis!C6 -> Selected: All / All | U10: =TEXT(MAX(Analysis!B28:B32),"$#,##0")&" revenue" -> $59,288 revenue
A12: KPI INDICATORS (vs Target) | M12: TOP 5 CUSTOMERS
A13: KPI | E13: Actual | G13: Target | I13: % of Target | K13: Status | M13: # | N13: Customer | S13: Revenue | V13: Share
A14: Total Revenue | E14: =Analysis!C17 -> 229192.47 | G14: 250000 | I14: =E14/G14 -> 0.91676988 | K14: =I14 -> 0.91676988 | M14: 1 | N14: =Analysis!B145 -> Mark Carter | S14: =Analysis!C145 -> 15659.65 | V14: =Analysis!E145 -> 0.068325325
A15: Avg Order Value | E15: =Analysis!C19 -> 916.76988 | G15: 900 | I15: =E15/G15 -> 1.0186332 | K15: =I15 -> 1.0186332 | M15: 2 | N15: =Analysis!B146 -> Edward Mitchell | S15: =Analysis!C146 -> 11919.77 | V15: =Analysis!E146 -> 0.052007686
A16: Repeat Customer Rate | E16: =Analysis!C161 -> 0.94 | G16: 0.9 | I16: =E16/G16 -> 1.0444444 | K16: =I16 -> 1.0444444 | M16: 3 | N16: =Analysis!B147 -> Barbara Young | S16: =Analysis!C147 -> 10649.8 | V16: =Analysis!E147 -> 0.046466623
A17: Transactions | E17: =Analysis!C18 -> 250 | G17: 350 | I17: =E17/G17 -> 0.71428571 | K17: =I17 -> 0.71428571 | M17: 4 | N17: =Analysis!B148 -> Patricia Moore | S17: =Analysis!C148 -> 9799.73 | V17: =Analysis!E148 -> 0.042757644
M18: 5 | N18: =Analysis!B149 -> Paul Baker | S18: =Analysis!C149 -> 8309.74 | V18: =Analysis!E149 -> 0.036256601
A20: SALES ANALYSIS
A53: REGION x CATEGORY REVENUE (heatmap) | M53: KEY INSIGHTS
A54: Region | D54: Appliances | F54: Electronics | H54: Furniture | J54: Total | M54: =Report!C5 -> Total revenue of $229,192 came from 250 transactions by 50 customers (average order $917).
A55: =Analysis!A28 -> Central | D55: =SUMIFS('Raw Data'!$N$2:$N$251,'Raw Data'!$K$2:$K$251,$A55,'Raw Data'!$G$2:$G$251,"Appliances") -> 1999.71 | F55: =SUMIFS('Raw Data'!$N$2:$N$251,'Raw Data'!$K$2:$K$251,$A55,'Raw Data'!$G$2:$G$251,"Electronics") -> 24889.33 | H55: =SUMIFS('Raw Data'!$N$2:$N$251,'Raw Data'!$K$2:$K$251,$A55,'Raw Data'!$G$2:$G$251,"Furniture") -> 14399.3 | J55: =SUM(D55:I55) -> 41288.34 | M55: =Report!C6 -> Top customer is Mark Carter ($15,660). The top 10 customers contribute 41% of revenue.
A56: =Analysis!A29 -> East | D56: =SUMIFS('Raw Data'!$N$2:$N$251,'Raw Data'!$K$2:$K$251,$A56,'Raw Data'!$G$2:$G$251,"Appliances") -> 2239.67 | F56: =SUMIFS('Raw Data'!$N$2:$N$251,'Raw Data'!$K$2:$K$251,$A56,'Raw Data'!$G$2:$G$251,"Electronics") -> 50649.01 | H56: =SUMIFS('Raw Data'!$N$2:$N$251,'Raw Data'!$K$2:$K$251,$A56,'Raw Data'!$G$2:$G$251,"Furniture") -> 6399.71 | J56: =SUM(D56:I56) -> 59288.39 | M56: =Report!C7 -> Most frequently purchased: Bookshelf (35 transactions). Highest revenue product: Laptop.
A57: =Analysis!A30 -> North | D57: =SUMIFS('Raw Data'!$N$2:$N$251,'Raw Data'!$K$2:$K$251,$A57,'Raw Data'!$G$2:$G$251,"Appliances") -> 1119.84 | F57: =SUMIFS('Raw Data'!$N$2:$N$251,'Raw Data'!$K$2:$K$251,$A57,'Raw Data'!$G$2:$G$251,"Electronics") -> 39239.04 | H57: =SUMIFS('Raw Data'!$N$2:$N$251,'Raw Data'!$K$2:$K$251,$A57,'Raw Data'!$G$2:$G$251,"Furniture") -> 10449.43 | J57: =SUM(D57:I57) -> 50808.31 | M57: =Report!C8 -> Best region: East ($59,288). Weakest: South ($36,399).
A58: =Analysis!A31 -> South | D58: =SUMIFS('Raw Data'!$N$2:$N$251,'Raw Data'!$K$2:$K$251,$A58,'Raw Data'!$G$2:$G$251,"Appliances") -> 1099.83 | F58: =SUMIFS('Raw Data'!$N$2:$N$251,'Raw Data'!$K$2:$K$251,$A58,'Raw Data'!$G$2:$G$251,"Electronics") -> 25549.32 | H58: =SUMIFS('Raw Data'!$N$2:$N$251,'Raw Data'!$K$2:$K$251,$A58,'Raw Data'!$G$2:$G$251,"Furniture") -> 9749.6 | J58: =SUM(D58:I58) -> 36398.75 | M58: =Report!C9 -> Electronics is the leading category with 75% of revenue.
A59: =Analysis!A32 -> West | D59: =SUMIFS('Raw Data'!$N$2:$N$251,'Raw Data'!$K$2:$K$251,$A59,'Raw Data'!$G$2:$G$251,"Appliances") -> 1879.69 | F59: =SUMIFS('Raw Data'!$N$2:$N$251,'Raw Data'!$K$2:$K$251,$A59,'Raw Data'!$G$2:$G$251,"Electronics") -> 31429.35 | H59: =SUMIFS('Raw Data'!$N$2:$N$251,'Raw Data'!$K$2:$K$251,$A59,'Raw Data'!$G$2:$G$251,"Furniture") -> 8099.64 | J59: =SUM(D59:I59) -> 41408.68 | M59: =Report!C13 -> Focus marketing on High-Value customers, bundle Electronics with Furniture (cross-sell), and replicate best-region practices in the weakest region.

Sheet Report
B1: Final Report - Insights & Storytelling
B4: Topic | C4: Insight
B5: Total Revenue | C5: ="Total revenue of "&TEXT(Analysis!C17,"$#,##0")&" came from "&Analysis!C18&" transactions by "&Analysis!C21&" customers (average order "&TEXT(Analysis!C19,"$#,##0")&")." -> Total revenue of $229,192 came from 250 transactions by 50 customers (average order $917).
B6: Top Customers | C6: ="Top customer is "&Analysis!B145&" ("&TEXT(Analysis!C145,"$#,##0")&"). The top 10 customers contribute "&TEXT(SUM(Analysis!E145:E154),"0%")&" of revenue." -> Top customer is Mark Carter ($15,660). The top 10 customers contribute 41% of revenue.
B7: Most Sold Products | C7: ="Most frequently purchased: "&Analysis!C157&" ("&Analysis!C158&" transactions). Highest revenue product: "&Analysis!C159&"." -> Most frequently purchased: Bookshelf (35 transactions). Highest revenue product: Laptop.
B8: Regional Sales | C8: ="Best region: "&INDEX(Analysis!A28:A32,MATCH(1,Analysis!G28:G32,0))&" ("&TEXT(MAX(Analysis!B28:B32),"$#,##0")&"). Weakest: "&INDEX(Analysis!A28:A32,MATCH(MAX(Analysis!G28:G32),Analysis!G28:G32,0))&" ("&TEXT(MIN(Analysis!B28:B32),"$#,##0")&")." -> Best region: East ($59,288). Weakest: South ($36,399).
B9: Category Mix | C9: =INDEX(Analysis!A37:A39,MATCH(1,Analysis!G37:G39,0))&" is the leading category with "&TEXT(MAX(Analysis!F37:F39),"0%")&" of revenue." -> Electronics is the leading category with 75% of revenue.
B10: Customer Loyalty | C10: =Analysis!C160&" of "&Analysis!C21&" customers ("&TEXT(Analysis!C161,"0%")&") bought more than once; "&Analysis!C163&" bought both Electronics and Furniture." -> 47 of 50 customers (94%) bought more than once; 34 bought both Electronics and Furniture.
B11: Trend | C11: ='What-If & Regression'!A60 -> 0
B12: Forecast | C12: ="Linear forecast for the next two months: "&TEXT('What-If & Regression'!C56,"$#,##0")&" and "&TEXT('What-If & Regression'!C57,"$#,##0")&"." -> Linear forecast for the next two months: $19,554 and $19,714.
B13: Recommendation | C13: Focus marketing on High-Value customers, bundle Electronics with Furniture (cross-sell), and replicate best-region practices in the weakest region.
